{
	"name": "reddit",
	"description": "Reddit /u02c8ru025bdu026at/, stylized as reddit, is an entertainment, social networking service and news website where registered community members can submit content, such as text posts or direct links. Only registered users can then vote submissions up or down to organize the posts and determine their position on the sites pages. Content entries are organized by areas of interest called subreddits.",
	"image": "http://www.redditstatic.com/about/assets/reddit-logo.png",
	"tags": ["news",
	"social"],
	"created": "2015-12-20",
	"modified": "2015-12-20",
	"url": "http://theapistack.com/reddit/apis.json",
	"specificationVersion": "0.14",
	"apis": [{
		"name": "reddit",
		"description": "Reddit /u02c8ru025bdu026at/, stylized as reddit, is an entertainment, social networking service and news website where registered community members can submit content, such as text posts or direct links. Only registered users can then vote submissions up or down to organize the posts and determine their position on the sites pages. Content entries are organized by areas of interest called subreddits.",
		"image": "http://www.redditstatic.com/about/assets/reddit-logo.png",
		"humanURL": "http://www.reddit.com",
		"baseURL": "http://www.reddit.com",
		"tags": ["news",
		"social"],
		"properties": [{
			"type": "X-authentication-overview",
			"url": "https://github.com/reddit/reddit/wiki/OAuth2"
		},
		{
			"type": "X-best-practices",
			"url": "https://github.com/reddit/reddit/wiki/API"
		},
		{
			"type": "X-api-explorer",
			"url": "https://apigee.com/console/reddit"
		},
		{
			"type": "X-portal",
			"url": "http://www.reddit.com/dev/api"
		},
		{
			"type": "X-github",
			"url": "https://github.com/reddit/"
		},
		{
			"type": "X-twitter",
			"url": "https://twitter.com/reddit"
		},
		{
			"type": "X-webinars",
			"url": "http://www.reddit.com"
		}],
		"contact": [{
			"FN": "reddit",
			"X-twitter": "https://twitter.com/reddit"
		}]
	},
	{
		"name": "Reddit Account API",
		"description": "",
		"image": "http://www.redditstatic.com/about/assets/reddit-logo.png",
		"humanURL": "",
		"baseURL": "http://www.reddit.com",
		"properties": [{
			"type": "Swagger",
			"url": "http://theapistack.com/data/reddit/reddit-account-api-swagger.json"
		}],
		"contact": [{
			"FN": "reddit",
			"X-twitter": "https://twitter.com/reddit"
		}]
	},
	{
		"name": "Reddit Catpcha API",
		"description": "",
		"image": "http://www.redditstatic.com/about/assets/reddit-logo.png",
		"humanURL": "",
		"baseURL": "http://www.reddit.com",
		"properties": [{
			"type": "Swagger",
			"url": "http://theapistack.com/data/reddit/reddit-catpcha-api-swagger.json"
		}],
		"contact": [{
			"FN": "reddit",
			"X-twitter": "https://twitter.com/reddit"
		}]
	},
	{
		"name": "Reddit Flair API",
		"description": "",
		"image": "http://www.redditstatic.com/about/assets/reddit-logo.png",
		"humanURL": "",
		"baseURL": "http://www.reddit.com",
		"properties": [{
			"type": "Swagger",
			"url": "http://theapistack.com/data/reddit/reddit-flair-api-swagger.json"
		}],
		"contact": [{
			"FN": "reddit",
			"X-twitter": "https://twitter.com/reddit"
		}]
	},
	{
		"name": "Reddit Gold API",
		"description": "",
		"image": "http://www.redditstatic.com/about/assets/reddit-logo.png",
		"humanURL": "",
		"baseURL": "http://www.reddit.com",
		"properties": [{
			"type": "Swagger",
			"url": "http://theapistack.com/data/reddit/reddit-gold-api-swagger.json"
		}],
		"contact": [{
			"FN": "reddit",
			"X-twitter": "https://twitter.com/reddit"
		}]
	},
	{
		"name": "Reddit Links & Comments API",
		"description": "",
		"image": "http://www.redditstatic.com/about/assets/reddit-logo.png",
		"humanURL": "",
		"baseURL": "http://www.reddit.com",
		"properties": [{
			"type": "Swagger",
			"url": "http://theapistack.com/data/reddit/reddit-links--comments-api-swagger.json"
		}],
		"contact": [{
			"FN": "reddit",
			"X-twitter": "https://twitter.com/reddit"
		}]
	},
	{
		"name": "Reddit Listings API",
		"description": "",
		"image": "http://www.redditstatic.com/about/assets/reddit-logo.png",
		"humanURL": "",
		"baseURL": "http://www.reddit.com",
		"properties": [{
			"type": "Swagger",
			"url": "http://theapistack.com/data/reddit/reddit-listings-api-swagger.json"
		}],
		"contact": [{
			"FN": "reddit",
			"X-twitter": "https://twitter.com/reddit"
		}]
	},
	{
		"name": "Reddit Live Threads API",
		"description": "",
		"image": "http://www.redditstatic.com/about/assets/reddit-logo.png",
		"humanURL": "",
		"baseURL": "http://www.reddit.com",
		"properties": [{
			"type": "Swagger",
			"url": "http://theapistack.com/data/reddit/reddit-live-threads-api-swagger.json"
		}],
		"contact": [{
			"FN": "reddit",
			"X-twitter": "https://twitter.com/reddit"
		}]
	},
	{
		"name": "Reddit Miscellaneous API",
		"description": "",
		"image": "http://www.redditstatic.com/about/assets/reddit-logo.png",
		"humanURL": "",
		"baseURL": "http://www.reddit.com",
		"properties": [{
			"type": "Swagger",
			"url": "http://theapistack.com/data/reddit/reddit-miscellaneous-api-swagger.json"
		}],
		"contact": [{
			"FN": "reddit",
			"X-twitter": "https://twitter.com/reddit"
		}]
	},
	{
		"name": "Reddit Moderation API",
		"description": "",
		"image": "http://www.redditstatic.com/about/assets/reddit-logo.png",
		"humanURL": "",
		"baseURL": "http://www.reddit.com",
		"properties": [{
			"type": "Swagger",
			"url": "http://theapistack.com/data/reddit/reddit-moderation-api-swagger.json"
		}],
		"contact": [{
			"FN": "reddit",
			"X-twitter": "https://twitter.com/reddit"
		}]
	},
	{
		"name": "Reddit Multis API",
		"description": "",
		"image": "http://www.redditstatic.com/about/assets/reddit-logo.png",
		"humanURL": "",
		"baseURL": "http://www.reddit.com",
		"properties": [{
			"type": "Swagger",
			"url": "http://theapistack.com/data/reddit/reddit-multis-api-swagger.json"
		}],
		"contact": [{
			"FN": "reddit",
			"X-twitter": "https://twitter.com/reddit"
		}]
	},
	{
		"name": "Reddit Private Messages API",
		"description": "",
		"image": "http://www.redditstatic.com/about/assets/reddit-logo.png",
		"humanURL": "",
		"baseURL": "http://www.reddit.com",
		"properties": [{
			"type": "Swagger",
			"url": "http://theapistack.com/data/reddit/reddit-private-messages-api-swagger.json"
		}],
		"contact": [{
			"FN": "reddit",
			"X-twitter": "https://twitter.com/reddit"
		}]
	},
	{
		"name": "Reddit Search API",
		"description": "",
		"image": "http://www.redditstatic.com/about/assets/reddit-logo.png",
		"humanURL": "",
		"baseURL": "http://www.reddit.com",
		"properties": [{
			"type": "Swagger",
			"url": "http://theapistack.com/data/reddit/reddit-search-api-swagger.json"
		}],
		"contact": [{
			"FN": "reddit",
			"X-twitter": "https://twitter.com/reddit"
		}]
	},
	{
		"name": "Reddit Subreddits API",
		"description": "",
		"image": "http://www.redditstatic.com/about/assets/reddit-logo.png",
		"humanURL": "",
		"baseURL": "http://www.reddit.com",
		"properties": [{
			"type": "Swagger",
			"url": "http://theapistack.com/data/reddit/reddit-subreddits-api-swagger.json"
		}],
		"contact": [{
			"FN": "reddit",
			"X-twitter": "https://twitter.com/reddit"
		}]
	},
	{
		"name": "Reddit Users API",
		"description": "",
		"image": "http://www.redditstatic.com/about/assets/reddit-logo.png",
		"humanURL": "",
		"baseURL": "http://www.reddit.com",
		"properties": [{
			"type": "Swagger",
			"url": "http://theapistack.com/data/reddit/reddit-users-api-swagger.json"
		}],
		"contact": [{
			"FN": "reddit",
			"X-twitter": "https://twitter.com/reddit"
		}]
	}],
	"include": [],
	"maintainers": [{
		"FN": "Kin",
		"X-twitter": "apievangelist",
		"email": "kin@email.com"
	}]
}