{
	"name": "PromptCloud",
	"description": "PromptCloud opeartes on &ldquo;Data as a Service&rdquo; (DaaS) model and deals with large-scale data crawl and extraction, using cutting-edge technologies and cloud computing solutions (Nutch, Hadoop, Lucene, Cassandra, etc). Its proprietary software employs machine learning techniques to extract meaningful information from the web in desired format. These data could be from reviews, blogs, product catalogs, social sites, travel data&mdash;basically anything and everything on WWW. It&rsquo;s a customized solution over simply being a mass-data crawler, so you only get the data you wish to see. The solution provides both deep crawl and refresh crawl of the web pages in a structured format.",
	"image": "http://kinlane-productions.s3.amazonaws.com/api-evangelist-site/company/logos/prompt-cloud-logo.png",
	"tags": ["scraping"],
	"created": "2015-01-01",
	"modified": "2015-01-01",
	"url": "http://theapistack.com/promptcloud/apis.json",
	"specificationVersion": "0.14",
	"apis": [{
		"name": "PromptCloud",
		"description": "PromptCloud opeartes on &ldquo;Data as a Service&rdquo; (DaaS) model and deals with large-scale data crawl and extraction, using cutting-edge technologies and cloud computing solutions (Nutch, Hadoop, Lucene, Cassandra, etc). Its proprietary software employs machine learning techniques to extract meaningful information from the web in desired format. These data could be from reviews, blogs, product catalogs, social sites, travel data&mdash;basically anything and everything on WWW. It&rsquo;s a customized solution over simply being a mass-data crawler, so you only get the data you wish to see. The solution provides both deep crawl and refresh crawl of the web pages in a structured format.",
		"image": "http://kinlane-productions.s3.amazonaws.com/api-evangelist-site/company/logos/prompt-cloud-logo.png",
		"humanURL": "http://promptcloud.com/",
		"baseURL": "https://www.promptcloud.com/promptcloud-api-documentation/",
		"tags": ["scraping"],
		"properties": [{
			"type": "X-twitter",
			"url": "https://twitter.com/promptcloud"
		},
		{
			"type": "X-blog",
			"url": "http://blog.promptcloud.com/"
		},
		{
			"type": "X-blogrss",
			"url": "http://blog.promptcloud.com/feeds/posts/default?alt=rss"
		},
		{
			"type": "X-github",
			"url": "https://github.com/promptcloud"
		},
		{
			"type": "X-developer-portal",
			"url": "https://www.promptcloud.com/promptcloud-api-documentation/"
		}],
		"contact": [{
			"FN": "PromptCloud",
			"X-twitter": "https://twitter.com/promptcloud"
		}]
	}],
	"maintainers": [{
		"FN": "Kin",
		"X-twitter": "apievangelist",
		"email": "kin@email.com"
	}]
}