{
	"name": "Mailjet",
	"description": "Mailjet is an all-in-one solution to send, track and deliver both marketing and transactional emails, providing infrastructure for scaling and optimizing email deliverability. Mailjet can be accessed either via an easy-to-use online drag-and-drop interface or via APIs that allow developers to integrate the ability to send, receive, store emails, and track on delivery, organize and track on operations. Mailjet provides a free trial for developers, and then tiered, unit based pricing for API services after that.",
	"image": "http:\/\/kinlane-productions.s3.amazonaws.com\/api-evangelist-site\/company\/843_logo.jpg",
	"x-open-ranking": "0",
	"tags": [
		"API-Stack"
	],
	"created": "2016-04-20",
	"modified": "2016-04-20",
	"url": "http:\/\/theapistack.com\/data\/mailjet\/apis.json",
	"specificationVersion": "0.14",
	"apis": [
		{
			"name": "Mailjet Messages API",
			"description": "Mailjet is a real-time Cloud Emailing platform: scalable, agile and flexible! Our unique algorithm boosts your deliverability and our platform provides in-depth insight so you can optimize more than ever. Because 20% of emails never reach the inbox Mailjet is a logical choice! Communication to and from our API is done through HTTP(S) GET and POST queries. We support different formats to choose from depending on your affinities : JSON, XML, serialized PHP, and CSV for some export functions. You can access our API from almost any programming language, and in just a few minutes with our plug and play libraries.\n",
			"image": "http:\/\/kinlane-productions.s3.amazonaws.com\/api-evangelist-site\/company\/843_logo.jpg",
			"humanURL": "http:\/\/dev.mailjet.com\/email-api\/v3\/message\/",
			"baseURL": "http:\/\/dev.mailjet.com\/email-api\/v3\/message\/",
			"tags": [
				"API-Stack"
			],
			"properties": [
				{
					"type": "x-openapi-spec-json",
					"url": "http:\/\/theapistack.com\/data\/mailjet\/mailjet-messages-api-openapi-spec.json"
				},
				{
					"type": "x-openapi-spec-yaml",
					"url": "https:\/\/github.com\/api-stack\/api-stack\/blob\/gh-pages\/_data\/mailjet\/mailjet-messages-api-openapi-spec.yaml"
				}
			]
		}
	],
	"x-common": [
		{
			"type": "x-blog",
			"url": "http:\/\/blog.mailjet.com\/"
		},
		{
			"type": "x-blog-rss-feed",
			"url": "http:\/\/blog.mailjet.com\/rss"
		},
		{
			"type": "x-portal",
			"url": "http:\/\/dev.mailjet.com\/"
		},
		{
			"type": "x-documentation",
			"url": "http:\/\/www.mailjet.com\/support"
		},
		{
			"type": "x-getting-started",
			"url": "http:\/\/www.mailjet.com\/signup"
		},
		{
			"type": "x-github",
			"url": "https:\/\/github.com\/mailjet"
		},
		{
			"type": "x-joomla",
			"url": "https:\/\/github.com\/mailjet\/joomla-mailjet-plugin-apiv3"
		},
		{
			"type": "x-status-dashboard",
			"url": "https:\/\/mailjet.statuspage.io\/"
		},
		{
			"type": "x-twitter",
			"url": "https:\/\/twitter.com\/mailjet"
		},
		{
			"type": "x-webinars",
			"url": "http:\/\/www.mailjet.com"
		},
		{
			"type": "x-white-papers",
			"url": "http:\/\/www.mailjet.com\/white-paper"
		},
		{
			"type": "x-wordpress",
			"url": "https:\/\/github.com\/mailjet\/wordpress-mailjet-plugin-apiv3"
		}
	],
	"include": [
		{
			"name": "Parent",
			"url": "http:\/\/theapistack.com\/apis.json"
		}
	],
	"maintainers": [
		{
			"FN": "Kin Lane",
			"x-twitter": "apievangelist",
			"email": "info@apievangelist.com"
		}
	]
}