{
	"swagger": "2.0",
	"info": {
		"title": "Mailjet Messages API",
		"description": "Allows you to list and view the details of a Message (an e-mail) processed by Mailjet",
		"termsOfService": null,
		"version": "v3"
	},
	"host": "api.mailjet.com",
	"basePath": "v3/REST/",
	"schemes": [
		"http"
	],
	"produces": [
		"application/json"
	],
	"consumes": [
		"application/json"
	],
	"paths": {
		"message{id}": {
			"get": {
				"summary": "Message Detail",
				"description": "View the details of a message.",
				"operationId": "",
				"parameters": [
					{
						"name": "id",
						"in": "path",
						"description": "Message ID.",
						"type": "string",
						"format": "string"
					}
				],
				"responses": {
					"200": {
						"description": "OK"
					}
				},
				"tags": [
					"Messaging",
					" Email"
				]
			}
		}
	},
	"definitions": [
	]
}