{
	"name": "Gigya",
	"description": "<p>Gigya provides websites with a complete social infrastructure that creates immersive social experiences for users and provides unparalleled customer insights for businesses. Gigya equips businesses like ABC, Pepsi, and Verizon with a comprehensive solution to socialize their online properties.</p>",
	"image": "http://kinlane-productions.s3.amazonaws.com/api-evangelist-site/company/600_logo.png",
	"tags": ["authentication",
	"facebook",
	"openid",
	"social",
	"social networking",
	"social sharing",
	"stack"],
	"created": "2014-12-31",
	"modified": "2014-12-31",
	"url": "http://theapistack.com/gigya/apis.json",
	"specificationVersion": "0.14",
	"apis": [{
		"name": "Gigya",
		"description": "<p>Gigya provides websites with a complete social infrastructure that creates immersive social experiences for users and provides unparalleled customer insights for businesses. Gigya equips businesses like ABC, Pepsi, and Verizon with a comprehensive solution to socialize their online properties.</p>",
		"image": "http://kinlane-productions.s3.amazonaws.com/api-evangelist-site/company/600_logo.png",
		"humanURL": "http://gigya.com/",
		"baseURL": "http://developers.gigya.com/",
		"tags": ["authentication",
		"facebook",
		"openid",
		"social",
		"social networking",
		"social sharing",
		"stack"],
		"properties": [{
			"type": "X-twitter",
			"url": "https://twitter.com/GigyaDev"
		},
		{
			"type": "X-blog",
			"url": "http://blog.gigya.com"
		},
		{
			"type": "X-blogrss",
			"url": "http://blog.gigya.com/feed/"
		},
		{
			"type": "X-github",
			"url": "https://github.com/gigya"
		},
		{
			"type": "X-developer-portal",
			"url": "http://developers.gigya.com/"
		}],
		"contact": [{
			"FN": "Gigya",
			"X-twitter": "https://twitter.com/GigyaDev"
		}]
	}],
	"maintainers": [{
		"FN": "Kin",
		"X-twitter": "apievangelist",
		"email": "kin@email.com"
	}]
}