{
	"name": "Aspose",
	"description": "Aspose aims to provide developers with top quality file format APIs complemented by fast and reliable technical support. We listen closely to developers worldwide and produce solutions that meet their complex needs. Aspose save developers programming with file formats time that they can put to better use meeting their organizations&rsquo; objectives.",
	"image": "http:\/\/kinlane-productions.s3.amazonaws.com\/api-evangelist-site\/company\/1865_logo.jpg",
	"x-open-ranking": "0",
	"tags": [
		"API-Stack"
	],
	"created": "2016-04-20",
	"modified": "2016-04-20",
	"url": "http:\/\/theapistack.com\/data\/aspose\/apis.json",
	"specificationVersion": "0.14",
	"apis": [
		{
			"name": "Aspose.Storage API",
			"description": "Aspose provides cloud-based services for document generation, conversion, and automation. It works with documents created in Microsoft Word, Microsoft Excel, Microsoft PowerPoint, Adobe, and OpenDocument. It is also designed to handle barcodes, optical character recognition (OCR), and email formats and protocols. The Aspose REST APIs enable users to integrate many document processing and management tasks into their applications. These tasks include, but are not limited to, document assembly, file conversion, text extraction, barcode generation, and email tracking.",
			"image": "http:\/\/kinlane-productions.s3.amazonaws.com\/api-evangelist-site\/company\/1865_logo.jpg",
			"humanURL": "http:\/\/www.aspose.com\/docs\/display\/rest\/Aspose+for+Cloud+File+Storage+API+Reference+%28v1.1%29",
			"baseURL": "http:\/\/www.aspose.com\/docs\/display\/rest\/Aspose+for+Cloud+File+Storage+API+Reference+%28v1.1%29",
			"tags": [
				"API-Stack"
			],
			"properties": [
				{
					"type": "x-openapi-spec-json",
					"url": "http:\/\/theapistack.com\/data\/aspose\/asposestorage-api-openapi-spec.json"
				},
				{
					"type": "x-openapi-spec-yaml",
					"url": "https:\/\/github.com\/api-stack\/api-stack\/blob\/gh-pages\/_data\/aspose\/asposestorage-api-openapi-spec.yaml"
				}
			]
		}
	],
	"x-common": [
		{
			"type": "x-blog",
			"url": "http:\/\/www.aspose.com\/community\/blogs\/default.aspx"
		},
		{
			"type": "x-blog-rss-feed",
			"url": "http:\/\/www.aspose.com\/community\/blogs\/rss.aspx"
		},
		{
			"type": "x-portal",
			"url": "http:\/\/www.aspose.com\/cloud\/total-api.aspx"
		},
		{
			"type": "x-forum",
			"url": "http:\/\/www.aspose.com\/community\/forums\/default.aspx"
		},
		{
			"type": "x-linkedin",
			"url": "http:\/\/www.linkedin.com\/company\/aspose-pty-ltd"
		},
		{
			"type": "x-twitter",
			"url": "https:\/\/twitter.com\/Aspose"
		},
		{
			"type": "x-videos",
			"url": "http:\/\/www.youtube.com\/user\/asposevideo"
		},
		{
			"type": "x-webinars",
			"url": "http:\/\/www.aspose.com"
		}
	],
	"include": [
		{
			"name": "Parent",
			"url": "http:\/\/theapistack.com\/apis.json"
		}
	],
	"maintainers": [
		{
			"FN": "Kin Lane",
			"x-twitter": "apievangelist",
			"email": "info@apievangelist.com"
		}
	]
}