{
	"name": "FUEL",
	"description": "Search, download, and serve thousands of photos and videos with an innovative API powered by EVOX Images, the ultimate source and leader in automotive imagery.",
	"image": "http://kinlane-productions.s3.amazonaws.com/api-evangelist-site/company/logos/fuel-logo.png",
	"tags": ["auto",
	"automobile"],
	"created": "2015-01-01",
	"modified": "2015-01-01",
	"url": "http://theapistack.com/fuel/apis.json",
	"specificationVersion": "0.14",
	"apis": [{
		"name": "Fuel API",
		"description": "",
		"image": "http://kinlane-productions.s3.amazonaws.com/api-evangelist-site/company/logos/fuel-logo.png",
		"humanURL": "http://fuelapi.com/",
		"baseURL": "http://fuelapi.com/",
		"tags": ["auto"],
		"properties": [{
			"type": "X-portal",
			"url": "http://fuelapi.com/documentation"
		},
		{
			"type": "X-twitter",
			"url": "https://twitter.com/fuelapi"
		},
		{
			"type": "X-webinars",
			"url": "http://fuelapi.com"
		}],
		"contact": [{
			"FN": "Fuel API",
			"X-twitter": "https://twitter.com/fuelapi"
		}]
	}],
	"maintainers": [{
		"FN": "Kin",
		"X-twitter": "apievangelist",
		"email": "kin@email.com"
	}]
}