{
	"name": "Delicious",
	"description": "Discover, remember, and showcase yourrnpassions from around the web.",
	"image": "http://kinlane-productions.s3.amazonaws.com/api-evangelist-site/company/179_logo.jpg",
	"tags": ["bookmarks",
	"links"],
	"created": "2014-12-31",
	"modified": "2014-12-31",
	"url": "http://theapistack.com/delicious/apis.json",
	"specificationVersion": "0.14",
	"apis": [{
		"name": "Delicious",
		"description": "<p><span>Delicious proudly offers one of the most powerful and flexible APIs on the web. With over a billion links served daily, our API integrates seamlessly with any website or app to easily read, add, query, and edit bookmarks.&nbsp;</span></p>",
		"image": "http://kinlane-productions.s3.amazonaws.com/api-evangelist-site/company/179_logo.jpg",
		"humanURL": "https://delicious.com",
		"baseURL": "https://delicious.com",
		"tags": ["bookmarks",
		"links"],
		"properties": [{
			"type": "X-application-gallery",
			"url": "https://delicious.com/apps"
		},
		{
			"type": "X-blog",
			"url": "http://blog.delicious.com/"
		},
		{
			"type": "X-blog-rss-feed",
			"url": "http://blog.delicious.com/feed/"
		},
		{
			"type": "X-branding",
			"url": "https://delicious.com/branding"
		},
		{
			"type": "X-portal",
			"url": "https://delicious.com/help/api"
		},
		{
			"type": "X-email",
			"url": "feedback@delicious.com"
		},
		{
			"type": "X-facebook",
			"url": "http://www.facebook.com/delicious"
		},
		{
			"type": "X-faq",
			"url": "https://delicious.com/help"
		},
		{
			"type": "X-github",
			"url": "https://github.com/SciDevs"
		},
		{
			"type": "X-google",
			"url": "https://plus.google.com/107396958691803506761/"
		},
		{
			"type": "X-privacy-policy",
			"url": "https://delicious.com/privacy"
		},
		{
			"type": "X-twitter",
			"url": "https://twitter.com/delicious"
		},
		{
			"type": "X-webinars",
			"url": "https://delicious.com"
		},
		{
			"type": "Swagger",
			"url": "http://theapistack.com/data/delicious/delicious-swagger.json"
		},
		{
			"type": "Swagger",
			"url": ""
		}],
		"contact": [{
			"FN": "Delicious",
			"email": "feedback@delicious.com",
			"X-twitter": "https://twitter.com/delicious"
		}]
	}],
	"maintainers": [{
		"FN": "Kin",
		"X-twitter": "apievangelist",
		"email": "kin@email.com"
	}]
}