{
	"id": "7ebff574-52b6-91bb-d71b-f7b10f3bf17f",
	"name": "Alchemy Authors Extraction API.",
	"description": "AlchemyAPI is capable of extracting author information from web pages.",
	"order": [],
	"folders": [
		{
			"id": "32ec781c-520a-1d57-7bf4-02ea5ea61021",
			"name": "url",
			"description": "Folder for url",
			"order": [
				"82c27dcc-f9a1-6bc9-8b0b-de6139ee3572"
			],
			"owner": "35240"
		}
	],
	"timestamp": 1413302258635,
	"owner": "35240",
	"hasRequests": true,
	"requests": [
		{
			"id": "82c27dcc-f9a1-6bc9-8b0b-de6139ee3572",
			"headers": "",
			"url": "http://access.alchemyapi.com/calls/url/URLGetAuthors",
			"pathVariables": {},
			"preRequestScript": "",
			"method": "GET",
			"data": [
				{
					"key": "size",
					"value": "original",
					"type": "text",
					"enabled": true
				}
			],
			"dataMode": "params",
			"description": "AlchemyAPI is capable of extracting author information from web pages.",
			"descriptionFormat": "html",
			"time": 1450932449548,
			"version": 2,
			"responses": [],
			"tests": "",
			"collectionId": "7ebff574-52b6-91bb-d71b-f7b10f3bf17f",
			"name": "Get Authors",
			"folder": "32ec781c-520a-1d57-7bf4-02ea5ea61021"
		}
	]
}