{
	"name": "Hootsuite",
	"description": "HootSuite is a social media management system for businesses and organizations to collaboratively execute campaigns across multiple social networks from one secure, web-based dashboard. Launch marketing campaigns, identify and grow audience, and distribute targeted messages using HootSuite&rsquo;s unique social media dashboard.",
	"image": "http://kinlane-productions.s3.amazonaws.com/api-evangelist-site/company/logos/hootsuite_logo_3581.gif",
	"tags": ["social",
	"stack"],
	"created": "2015-01-01",
	"modified": "2015-01-01",
	"url": "http://theapistack.com/hootsuite/apis.json",
	"specificationVersion": "0.14",
	"apis": [{
		"name": "Hootsuite",
		"description": "HootSuite is a social media management system for businesses and organizations to collaboratively execute campaigns across multiple social networks from one secure, web-based dashboard. Launch marketing campaigns, identify and grow audience, and distribute targeted messages using HootSuite&rsquo;s unique social media dashboard.",
		"image": "http://kinlane-productions.s3.amazonaws.com/api-evangelist-site/company/logos/hootsuite_logo_3581.gif",
		"humanURL": "http://hootsuite.com",
		"baseURL": "https://hootsuite.com/developers/app-directory",
		"tags": ["social",
		"stack"],
		"properties": [{
			"type": "X-twitter",
			"url": "https://twitter.com/#!/HootSuite"
		},
		{
			"type": "X-blog",
			"url": "http://blog.hootsuite.com"
		},
		{
			"type": "X-blogrss",
			"url": "http://blog.hootsuite.com/feed/"
		},
		{
			"type": "X-github",
			"url": "https://github.com/hootsuite"
		},
		{
			"type": "X-developer-portal",
			"url": "https://hootsuite.com/developers/app-directory"
		}],
		"contact": [{
			"FN": "Hootsuite",
			"X-twitter": "https://twitter.com/#!/HootSuite"
		}]
	}],
	"maintainers": [{
		"FN": "Kin",
		"X-twitter": "apievangelist",
		"email": "kin@email.com"
	}]
}