{
	"name": "CallTrackingMetrics",
	"description": "Do you get customers & leads over the phone? Track what ad campaigns are prompting people to call you and better optimize your advertising budgets!",
	"image": "http://kinlane-productions.s3.amazonaws.com/api-evangelist-site/company/logos/call-tracking-metrics.png",
	"tags": ["analytics",
	"stack",
	"telephony",
	"twilio"],
	"created": "2015-01-01",
	"modified": "2015-01-01",
	"url": "http://theapistack.com/calltrackingmetrics/apis.json",
	"specificationVersion": "0.14",
	"apis": [{
		"name": "CallTrackingMetrics",
		"description": "Do you get customers & leads over the phone? Track what ad campaigns are prompting people to call you and better optimize your advertising budgets!",
		"image": "http://kinlane-productions.s3.amazonaws.com/api-evangelist-site/company/logos/call-tracking-metrics.png",
		"humanURL": "https://calltrackingmetrics.com/",
		"baseURL": "https://calltrackingmetrics.com/integration",
		"tags": ["analytics",
		"stack",
		"telephony",
		"twilio"],
		"properties": [{
			"type": "X-twitter",
			"url": "https://twitter.com/CallTrac"
		},
		{
			"type": "X-blog",
			"url": "http://blog.calltrackingmetrics.com/"
		},
		{
			"type": "X-blogrss",
			"url": "http://blog.calltrackingmetrics.com/feed"
		},
		{
			"type": "X-developer-portal",
			"url": "https://calltrackingmetrics.com/integration"
		}],
		"contact": [{
			"FN": "CallTrackingMetrics",
			"X-twitter": "https://twitter.com/CallTrac"
		}]
	}],
	"maintainers": [{
		"FN": "Kin",
		"X-twitter": "apievangelist",
		"email": "kin@email.com"
	}]
}