{
	"name": "RoboWhois",
	"description": "RoboWhois is a cloud-based web service that provides a RESTful API to access WHOIS records and domain related information with a unified, consistent interface.",
	"image": "http://kinlane-productions.s3.amazonaws.com/api-evangelist-site/company/logos/robo-whois.png",
	"tags": ["domain",
	"domain names",
	"domains",
	"http post",
	"stack",
	"whois"],
	"created": "2015-01-01",
	"modified": "2015-01-01",
	"url": "http://theapistack.com/robowhois/apis.json",
	"specificationVersion": "0.14",
	"apis": [{
		"name": "RoboWhois",
		"description": "RoboWhois is a cloud-based web service that provides a RESTful API to access WHOIS records and domain related information with a unified, consistent interface.",
		"image": "http://kinlane-productions.s3.amazonaws.com/api-evangelist-site/company/logos/robo-whois.png",
		"humanURL": "http://www.robowhois.com/",
		"baseURL": "https://www.robowhois.com/docs/api/",
		"tags": ["domain",
		"domain names",
		"domains",
		"http post",
		"stack",
		"whois"],
		"properties": [{
			"type": "X-twitter",
			"url": "https://twitter.com/robowhois"
		},
		{
			"type": "X-github",
			"url": "https://github.com/robowhois"
		},
		{
			"type": "X-developer-portal",
			"url": "https://www.robowhois.com/docs/api/"
		}],
		"contact": [{
			"FN": "RoboWhois",
			"X-twitter": "https://twitter.com/robowhois"
		}]
	}],
	"maintainers": [{
		"FN": "Kin",
		"X-twitter": "apievangelist",
		"email": "kin@email.com"
	}]
}