{
	"name": "Coinable Exchange",
	"description": "Coinable Exchange - A U.S. Based Bitcoin Exchange. A safe and secure bitcoin exchange run by Coinbase, the leading bitcoin company. Coinbase is insured against hacking, internal theft, and accidental loss in an amount that covers maximum value of bitcoin we hold in online storage at any given time. Welcome to Coinbase Exchange trader and developer documentation. These documents outline exchange functionality, market details, and APIs. APIs are separated into two categories: trading and feed. Trading APIs require authentication and provide access to placing orders and other account information. Feed APIs provide market data and are public.",
	"image": "",
	"tags": ["bitcoin",
	"blockchain"],
	"created": "2015-05-17",
	"modified": "2015-05-17",
	"url": "http://theapistack.com/coinable-exchange/apis.json",
	"specificationVersion": "0.14",
	"apis": [{
		"name": "Coinable Exchange",
		"description": "Coinable Exchange - A U.S. Based Bitcoin Exchange. A safe and secure bitcoin exchange run by Coinbase, the leading bitcoin company. Coinbase is insured against hacking, internal theft, and accidental loss in an amount that covers maximum value of bitcoin we hold in online storage at any given time. Welcome to Coinbase Exchange trader and developer documentation. These documents outline exchange functionality, market details, and APIs. APIs are separated into two categories: trading and feed. Trading APIs require authentication and provide access to placing orders and other account information. Feed APIs provide market data and are public.",
		"image": "",
		"humanURL": "https://exchange.coinbase.com/",
		"baseURL": "https://docs.exchange.coinbase.com/",
		"tags": ["bitcoin",
		"blockchain"],
		"properties": [{
			"type": "X-developer-portal",
			"url": "https://docs.exchange.coinbase.com/"
		}],
		"contact": [{
			"FN": "Coinable Exchange"
		}]
	}],
	"maintainers": [{
		"FN": "Kin",
		"X-twitter": "apievangelist",
		"email": "kin@email.com"
	}]
}